[
  {
    "id": "en-al-jalalayn-44-1",
    "bookId": "en-al-jalalayn",
    "language": "en",
    "surah": 44,
    "fromAyah": 1,
    "toAyah": 1,
    "title": "Tafsir Al-Jalalayn — English · 44:1",
    "body": "Hā mīm God knows best what He means by these letters.",
    "sourceLabel": "Tafsir Al-Jalalayn — English",
    "tags": [
      "en-al-jalalayn",
      "en",
      "foundational"
    ]
  },
  {
    "id": "en-al-jalalayn-44-10",
    "bookId": "en-al-jalalayn",
    "language": "en",
    "surah": 44,
    "fromAyah": 10,
    "toAyah": 10,
    "title": "Tafsir Al-Jalalayn — English · 44:10",
    "body": "God exalted be He says So watch out for the day when the heaven will produce a visible smoke. Thus the earth became barren and famine became so severe that they began to see what looked like smoke rising between the heaven and the earth",
    "sourceLabel": "Tafsir Al-Jalalayn — English",
    "tags": [
      "en-al-jalalayn",
      "en",
      "foundational"
    ]
  },
  {
    "id": "en-al-jalalayn-44-11",
    "bookId": "en-al-jalalayn",
    "language": "en",
    "surah": 44,
    "fromAyah": 11,
    "toAyah": 11,
    "title": "Tafsir Al-Jalalayn — English · 44:11",
    "body": "that will envelop the people and so they said ‘This is a painful chastisement!",
    "sourceLabel": "Tafsir Al-Jalalayn — English",
    "tags": [
      "en-al-jalalayn",
      "en",
      "foundational"
    ]
  },
  {
    "id": "en-al-jalalayn-44-12",
    "bookId": "en-al-jalalayn",
    "language": "en",
    "surah": 44,
    "fromAyah": 12,
    "toAyah": 12,
    "title": "Tafsir Al-Jalalayn — English · 44:12",
    "body": "Our Lord relieve us from the chastisement; indeed we have believed’ we have now affirmed the sincerity of Your Prophet.",
    "sourceLabel": "Tafsir Al-Jalalayn — English",
    "tags": [
      "en-al-jalalayn",
      "en",
      "foundational"
    ]
  },
  {
    "id": "en-al-jalalayn-44-13",
    "bookId": "en-al-jalalayn",
    "language": "en",
    "surah": 44,
    "fromAyah": 13,
    "toAyah": 13,
    "title": "Tafsir Al-Jalalayn — English · 44:13",
    "body": "God exalted be He says How can there be a reminder for them that is to say faith will not benefit them once the chastisement has been sent down when already there has come to them a manifest Messenger whose Message is plain to understand",
    "sourceLabel": "Tafsir Al-Jalalayn — English",
    "tags": [
      "en-al-jalalayn",
      "en",
      "foundational"
    ]
  },
  {
    "id": "en-al-jalalayn-44-14",
    "bookId": "en-al-jalalayn",
    "language": "en",
    "surah": 44,
    "fromAyah": 14,
    "toAyah": 14,
    "title": "Tafsir Al-Jalalayn — English · 44:14",
    "body": "but they turned away from him and said ‘He has been taught — that is a human being is teaching him the Qur’ān — he is a madman!’",
    "sourceLabel": "Tafsir Al-Jalalayn — English",
    "tags": [
      "en-al-jalalayn",
      "en",
      "foundational"
    ]
  },
  {
    "id": "en-al-jalalayn-44-15",
    "bookId": "en-al-jalalayn",
    "language": "en",
    "surah": 44,
    "fromAyah": 15,
    "toAyah": 15,
    "title": "Tafsir Al-Jalalayn — English · 44:15",
    "body": "‘Indeed We will remove the chastisement the famine from you for a little time; and so it was removed from them. But you will indeed revert!’ to your disbelief — and they did.",
    "sourceLabel": "Tafsir Al-Jalalayn — English",
    "tags": [
      "en-al-jalalayn",
      "en",
      "foundational"
    ]
  },
  {
    "id": "en-al-jalalayn-44-16",
    "bookId": "en-al-jalalayn",
    "language": "en",
    "surah": 44,
    "fromAyah": 16,
    "toAyah": 16,
    "title": "Tafsir Al-Jalalayn — English · 44:16",
    "body": "Mention the day when We shall assault with the most mighty assault — this was the day of the battle of Badr — then indeed We shall take vengeance on them al-batsh means ‘to seize violently’.",
    "sourceLabel": "Tafsir Al-Jalalayn — English",
    "tags": [
      "en-al-jalalayn",
      "en",
      "foundational"
    ]
  },
  {
    "id": "en-al-jalalayn-44-17",
    "bookId": "en-al-jalalayn",
    "language": "en",
    "surah": 44,
    "fromAyah": 17,
    "toAyah": 17,
    "title": "Tafsir Al-Jalalayn — English · 44:17",
    "body": "And certainly We tried We tested before them the people of Pharaoh together with him when a messenger came to them namely Moses peace be upon him who was honoured before God exalted be He",
    "sourceLabel": "Tafsir Al-Jalalayn — English",
    "tags": [
      "en-al-jalalayn",
      "en",
      "foundational"
    ]
  },
  {
    "id": "en-al-jalalayn-44-18",
    "bookId": "en-al-jalalayn",
    "language": "en",
    "surah": 44,
    "fromAyah": 18,
    "toAyah": 18,
    "title": "Tafsir Al-Jalalayn — English · 44:18",
    "body": "saying ‘Give over to me what I summon you to in the way of faith that is manifest your faith to me O servants of God; indeed I am for you a messenger who is faithful’ in what he has been sent with",
    "sourceLabel": "Tafsir Al-Jalalayn — English",
    "tags": [
      "en-al-jalalayn",
      "en",
      "foundational"
    ]
  },
  {
    "id": "en-al-jalalayn-44-19",
    "bookId": "en-al-jalalayn",
    "language": "en",
    "surah": 44,
    "fromAyah": 19,
    "toAyah": 19,
    "title": "Tafsir Al-Jalalayn — English · 44:19",
    "body": "and ‘Do not rebel do not try to act strong against God by neglecting obedience to Him. Lo! I bring you a clear warrant’ clear proof of the sincerity of my Mission — but they threatened to stone him to death.",
    "sourceLabel": "Tafsir Al-Jalalayn — English",
    "tags": [
      "en-al-jalalayn",
      "en",
      "foundational"
    ]
  },
  {
    "id": "en-al-jalalayn-44-2",
    "bookId": "en-al-jalalayn",
    "language": "en",
    "surah": 44,
    "fromAyah": 2,
    "toAyah": 2,
    "title": "Tafsir Al-Jalalayn — English · 44:2",
    "body": "By the Book the Qur’ān that clarifies the one that distinguishes what is lawful from what is unlawful.",
    "sourceLabel": "Tafsir Al-Jalalayn — English",
    "tags": [
      "en-al-jalalayn",
      "en",
      "foundational"
    ]
  },
  {
    "id": "en-al-jalalayn-44-20",
    "bookId": "en-al-jalalayn",
    "language": "en",
    "surah": 44,
    "fromAyah": 20,
    "toAyah": 20,
    "title": "Tafsir Al-Jalalayn — English · 44:20",
    "body": "So he said ‘And truly I seek refuge in my Lord and your Lord lest you should stone me to death with rocks.",
    "sourceLabel": "Tafsir Al-Jalalayn — English",
    "tags": [
      "en-al-jalalayn",
      "en",
      "foundational"
    ]
  },
  {
    "id": "en-al-jalalayn-44-21",
    "bookId": "en-al-jalalayn",
    "language": "en",
    "surah": 44,
    "fromAyah": 21,
    "toAyah": 21,
    "title": "Tafsir Al-Jalalayn — English · 44:21",
    "body": "And if you do not believe me then stay away from me’ that is then refrain from harming me — but they did not refrain from such action.",
    "sourceLabel": "Tafsir Al-Jalalayn — English",
    "tags": [
      "en-al-jalalayn",
      "en",
      "foundational"
    ]
  },
  {
    "id": "en-al-jalalayn-44-22",
    "bookId": "en-al-jalalayn",
    "language": "en",
    "surah": 44,
    "fromAyah": 22,
    "toAyah": 22,
    "title": "Tafsir Al-Jalalayn — English · 44:22",
    "body": "So he called to his Lord saying ‘These are indeed a guilty an idolatrous lot!’",
    "sourceLabel": "Tafsir Al-Jalalayn — English",
    "tags": [
      "en-al-jalalayn",
      "en",
      "foundational"
    ]
  },
  {
    "id": "en-al-jalalayn-44-23",
    "bookId": "en-al-jalalayn",
    "language": "en",
    "surah": 44,
    "fromAyah": 23,
    "toAyah": 23,
    "title": "Tafsir Al-Jalalayn — English · 44:23",
    "body": "God exalted be He said ‘Then set out read fa-asri or fa’sri with My servants the Children of Israel by night; for you will assuredly be pursued surely Pharaoh and his people will pursue you.",
    "sourceLabel": "Tafsir Al-Jalalayn — English",
    "tags": [
      "en-al-jalalayn",
      "en",
      "foundational"
    ]
  },
  {
    "id": "en-al-jalalayn-44-24",
    "bookId": "en-al-jalalayn",
    "language": "en",
    "surah": 44,
    "fromAyah": 24,
    "toAyah": 24,
    "title": "Tafsir Al-Jalalayn — English · 44:24",
    "body": "And leave the sea behind once you and your companions have crossed it at rest still and calm until the Egyptians enter it indeed they will be a drowned host’ — he Moses was reassured by this statement — and they were indeed drowned.",
    "sourceLabel": "Tafsir Al-Jalalayn — English",
    "tags": [
      "en-al-jalalayn",
      "en",
      "foundational"
    ]
  },
  {
    "id": "en-al-jalalayn-44-25",
    "bookId": "en-al-jalalayn",
    "language": "en",
    "surah": 44,
    "fromAyah": 25,
    "toAyah": 25,
    "title": "Tafsir Al-Jalalayn — English · 44:25",
    "body": "How many gardens orchards and flowing fountains did they leave behind",
    "sourceLabel": "Tafsir Al-Jalalayn — English",
    "tags": [
      "en-al-jalalayn",
      "en",
      "foundational"
    ]
  },
  {
    "id": "en-al-jalalayn-44-26",
    "bookId": "en-al-jalalayn",
    "language": "en",
    "surah": 44,
    "fromAyah": 26,
    "toAyah": 26,
    "title": "Tafsir Al-Jalalayn — English · 44:26",
    "body": "as well as sown fields and many a glorious residence many a splendid court",
    "sourceLabel": "Tafsir Al-Jalalayn — English",
    "tags": [
      "en-al-jalalayn",
      "en",
      "foundational"
    ]
  },
  {
    "id": "en-al-jalalayn-44-27",
    "bookId": "en-al-jalalayn",
    "language": "en",
    "surah": 44,
    "fromAyah": 27,
    "toAyah": 27,
    "title": "Tafsir Al-Jalalayn — English · 44:27",
    "body": "and the bounty the comforts in which they rejoiced! in which they lived luxuriously.",
    "sourceLabel": "Tafsir Al-Jalalayn — English",
    "tags": [
      "en-al-jalalayn",
      "en",
      "foundational"
    ]
  },
  {
    "id": "en-al-jalalayn-44-28",
    "bookId": "en-al-jalalayn",
    "language": "en",
    "surah": 44,
    "fromAyah": 28,
    "toAyah": 28,
    "title": "Tafsir Al-Jalalayn — English · 44:28",
    "body": "So it was kadhālika is the predicate of a subject that is missing such as ‘the matter was so’ and We made these an inheritance that is to say their riches for another people namely the Children of Israel.",
    "sourceLabel": "Tafsir Al-Jalalayn — English",
    "tags": [
      "en-al-jalalayn",
      "en",
      "foundational"
    ]
  },
  {
    "id": "en-al-jalalayn-44-29",
    "bookId": "en-al-jalalayn",
    "language": "en",
    "surah": 44,
    "fromAyah": 29,
    "toAyah": 29,
    "title": "Tafsir Al-Jalalayn — English · 44:29",
    "body": "So neither the heaven nor the earth wept for them — in contrast to the case with believers at the point of whose death weep both their places of prayer on earth and the route by which their deeds ascend the heaven; nor were they reprieved nor were they deferred until they were able to make repentance.",
    "sourceLabel": "Tafsir Al-Jalalayn — English",
    "tags": [
      "en-al-jalalayn",
      "en",
      "foundational"
    ]
  },
  {
    "id": "en-al-jalalayn-44-3",
    "bookId": "en-al-jalalayn",
    "language": "en",
    "surah": 44,
    "fromAyah": 3,
    "toAyah": 3,
    "title": "Tafsir Al-Jalalayn — English · 44:3",
    "body": "Indeed We revealed it on a blessed night the Night of Ordainment laylat al-qadr or the eve of the middle of Sha‘bān in which it was revealed from the Mother Book from the seventh heaven to the heaven of this world. Indeed We have been warning We have been causing people by it to have fear of God.",
    "sourceLabel": "Tafsir Al-Jalalayn — English",
    "tags": [
      "en-al-jalalayn",
      "en",
      "foundational"
    ]
  },
  {
    "id": "en-al-jalalayn-44-30",
    "bookId": "en-al-jalalayn",
    "language": "en",
    "surah": 44,
    "fromAyah": 30,
    "toAyah": 30,
    "title": "Tafsir Al-Jalalayn — English · 44:30",
    "body": "And verily We delivered the Children of Israel from the humiliating chastisement of having their children slain and their womenfolk taken as servants",
    "sourceLabel": "Tafsir Al-Jalalayn — English",
    "tags": [
      "en-al-jalalayn",
      "en",
      "foundational"
    ]
  },
  {
    "id": "en-al-jalalayn-44-31",
    "bookId": "en-al-jalalayn",
    "language": "en",
    "surah": 44,
    "fromAyah": 31,
    "toAyah": 31,
    "title": "Tafsir Al-Jalalayn — English · 44:31",
    "body": "from Pharaoh min Fir‘awna is said to be a substitution for al-‘adhābi on the basis of an implied annexation that is to say min ‘adhābi Fir‘awna; or it is said to be a circumstantial qualifier referring to al-‘adhāb ‘the chastisement’. Truly he was a tyrant of the wanton ones.",
    "sourceLabel": "Tafsir Al-Jalalayn — English",
    "tags": [
      "en-al-jalalayn",
      "en",
      "foundational"
    ]
  },
  {
    "id": "en-al-jalalayn-44-32",
    "bookId": "en-al-jalalayn",
    "language": "en",
    "surah": 44,
    "fromAyah": 32,
    "toAyah": 32,
    "title": "Tafsir Al-Jalalayn — English · 44:32",
    "body": "And verily We chose them that is the Children of Israel with a knowledge that We had of their state over all the worlds that is the worlds of their time those of the rational beings.",
    "sourceLabel": "Tafsir Al-Jalalayn — English",
    "tags": [
      "en-al-jalalayn",
      "en",
      "foundational"
    ]
  },
  {
    "id": "en-al-jalalayn-44-33",
    "bookId": "en-al-jalalayn",
    "language": "en",
    "surah": 44,
    "fromAyah": 33,
    "toAyah": 33,
    "title": "Tafsir Al-Jalalayn — English · 44:33",
    "body": "And We gave them signs in which there was a manifest trial an obvious grace such as the parting of the sea the sending down of manna and quails and other such signs.",
    "sourceLabel": "Tafsir Al-Jalalayn — English",
    "tags": [
      "en-al-jalalayn",
      "en",
      "foundational"
    ]
  },
  {
    "id": "en-al-jalalayn-44-34",
    "bookId": "en-al-jalalayn",
    "language": "en",
    "surah": 44,
    "fromAyah": 34,
    "toAyah": 34,
    "title": "Tafsir Al-Jalalayn — English · 44:34",
    "body": "Indeed these ones that is the Meccan disbelievers say",
    "sourceLabel": "Tafsir Al-Jalalayn — English",
    "tags": [
      "en-al-jalalayn",
      "en",
      "foundational"
    ]
  },
  {
    "id": "en-al-jalalayn-44-35",
    "bookId": "en-al-jalalayn",
    "language": "en",
    "surah": 44,
    "fromAyah": 35,
    "toAyah": 35,
    "title": "Tafsir Al-Jalalayn — English · 44:35",
    "body": "‘It that death after which there is life is nothing more than our first death that is when they were sperm-drops and we shall not be resurrected we shall not be raised alive after the second one.",
    "sourceLabel": "Tafsir Al-Jalalayn — English",
    "tags": [
      "en-al-jalalayn",
      "en",
      "foundational"
    ]
  },
  {
    "id": "en-al-jalalayn-44-36",
    "bookId": "en-al-jalalayn",
    "language": "en",
    "surah": 44,
    "fromAyah": 36,
    "toAyah": 36,
    "title": "Tafsir Al-Jalalayn — English · 44:36",
    "body": "Bring us then our fathers alive if you are being truthful’ about our being resurrected after we have died that is to say that we will be given life again.",
    "sourceLabel": "Tafsir Al-Jalalayn — English",
    "tags": [
      "en-al-jalalayn",
      "en",
      "foundational"
    ]
  },
  {
    "id": "en-al-jalalayn-44-37",
    "bookId": "en-al-jalalayn",
    "language": "en",
    "surah": 44,
    "fromAyah": 37,
    "toAyah": 37,
    "title": "Tafsir Al-Jalalayn — English · 44:37",
    "body": "God exalted be He says Are they better or the people of Tubba‘ — he was a prophet or a righteous man — and those communities before them? We destroyed because of their disbelief. In other words they are not mightier than those and yet they were destroyed; indeed they were criminals.",
    "sourceLabel": "Tafsir Al-Jalalayn — English",
    "tags": [
      "en-al-jalalayn",
      "en",
      "foundational"
    ]
  },
  {
    "id": "en-al-jalalayn-44-38",
    "bookId": "en-al-jalalayn",
    "language": "en",
    "surah": 44,
    "fromAyah": 38,
    "toAyah": 38,
    "title": "Tafsir Al-Jalalayn — English · 44:38",
    "body": "And We did not create the heavens and the earth and all that is between them intending to play by creating all that lā‘ibīna ‘to play’ is a circumstantial qualifier.",
    "sourceLabel": "Tafsir Al-Jalalayn — English",
    "tags": [
      "en-al-jalalayn",
      "en",
      "foundational"
    ]
  },
  {
    "id": "en-al-jalalayn-44-39",
    "bookId": "en-al-jalalayn",
    "language": "en",
    "surah": 44,
    "fromAyah": 39,
    "toAyah": 39,
    "title": "Tafsir Al-Jalalayn — English · 44:39",
    "body": "We did not create them and all that is between them except with the truth that is to say We created them rightfully so that one might infer thereby Our power and Our Oneness and other matters; but most of them that is the Meccan disbelievers do not know.",
    "sourceLabel": "Tafsir Al-Jalalayn — English",
    "tags": [
      "en-al-jalalayn",
      "en",
      "foundational"
    ]
  },
  {
    "id": "en-al-jalalayn-44-4",
    "bookId": "en-al-jalalayn",
    "language": "en",
    "surah": 44,
    "fromAyah": 4,
    "toAyah": 4,
    "title": "Tafsir Al-Jalalayn — English · 44:4",
    "body": "In it that is to say on the Night of Ordainment or on the eve of the middle of Sha‘bān every definitive matter that has been fixed with regard to the provisions and the terms of life and other things decreed by God for the entire year until that same night again the following year is distinguished is decided.",
    "sourceLabel": "Tafsir Al-Jalalayn — English",
    "tags": [
      "en-al-jalalayn",
      "en",
      "foundational"
    ]
  },
  {
    "id": "en-al-jalalayn-44-40",
    "bookId": "en-al-jalalayn",
    "language": "en",
    "surah": 44,
    "fromAyah": 40,
    "toAyah": 40,
    "title": "Tafsir Al-Jalalayn — English · 44:40",
    "body": "Assuredly the Day of Decision the Day of Resurrection in which God will decide between servants will be the tryst for all of them for everlasting chastisement;",
    "sourceLabel": "Tafsir Al-Jalalayn — English",
    "tags": [
      "en-al-jalalayn",
      "en",
      "foundational"
    ]
  },
  {
    "id": "en-al-jalalayn-44-41",
    "bookId": "en-al-jalalayn",
    "language": "en",
    "surah": 44,
    "fromAyah": 41,
    "toAyah": 41,
    "title": "Tafsir Al-Jalalayn — English · 44:41",
    "body": "the day when a friend will not avail a friend on account of kinship or friendship that is to say the day when he will not be able to ward off from the other anything of the chastisement nor will they be helped — nor will they be protected from it yawma ‘the day’ is a substitution for yawma’l-fasl ‘the Day of Decision’",
    "sourceLabel": "Tafsir Al-Jalalayn — English",
    "tags": [
      "en-al-jalalayn",
      "en",
      "foundational"
    ]
  },
  {
    "id": "en-al-jalalayn-44-42",
    "bookId": "en-al-jalalayn",
    "language": "en",
    "surah": 44,
    "fromAyah": 42,
    "toAyah": 42,
    "title": "Tafsir Al-Jalalayn — English · 44:42",
    "body": "except for him on whom God has mercy — and these are the believers for they will intercede for one another with God’s permission. He is indeed the Mighty the Victor in His retribution of the disbelievers the Merciful to believers.",
    "sourceLabel": "Tafsir Al-Jalalayn — English",
    "tags": [
      "en-al-jalalayn",
      "en",
      "foundational"
    ]
  },
  {
    "id": "en-al-jalalayn-44-43",
    "bookId": "en-al-jalalayn",
    "language": "en",
    "surah": 44,
    "fromAyah": 43,
    "toAyah": 43,
    "title": "Tafsir Al-Jalalayn — English · 44:43",
    "body": "Lo! the tree of Zaqqūm one of the vilest of the bitter trees of the Tihāma region God exalted be He will make it grow forth in the Hell-fire",
    "sourceLabel": "Tafsir Al-Jalalayn — English",
    "tags": [
      "en-al-jalalayn",
      "en",
      "foundational"
    ]
  },
  {
    "id": "en-al-jalalayn-44-44",
    "bookId": "en-al-jalalayn",
    "language": "en",
    "surah": 44,
    "fromAyah": 44,
    "toAyah": 44,
    "title": "Tafsir Al-Jalalayn — English · 44:44",
    "body": "will be the food of the sinful Abū Jahl and his companions the gravest of sinners.",
    "sourceLabel": "Tafsir Al-Jalalayn — English",
    "tags": [
      "en-al-jalalayn",
      "en",
      "foundational"
    ]
  },
  {
    "id": "en-al-jalalayn-44-45",
    "bookId": "en-al-jalalayn",
    "language": "en",
    "surah": 44,
    "fromAyah": 45,
    "toAyah": 45,
    "title": "Tafsir Al-Jalalayn — English · 44:45",
    "body": "Like molten copper that is to say like the dregs of black oil ka’l-muhli is the second predicate it will boil inside the bellies if read taghlī then it is a third predicate; if yaghlī then it is a circumstantial qualifier referring to al-muhl ‘molten copper’",
    "sourceLabel": "Tafsir Al-Jalalayn — English",
    "tags": [
      "en-al-jalalayn",
      "en",
      "foundational"
    ]
  },
  {
    "id": "en-al-jalalayn-44-46",
    "bookId": "en-al-jalalayn",
    "language": "en",
    "surah": 44,
    "fromAyah": 46,
    "toAyah": 46,
    "title": "Tafsir Al-Jalalayn — English · 44:46",
    "body": "as the boiling of boiling water hamīm means water of the most extreme temperature.",
    "sourceLabel": "Tafsir Al-Jalalayn — English",
    "tags": [
      "en-al-jalalayn",
      "en",
      "foundational"
    ]
  },
  {
    "id": "en-al-jalalayn-44-47",
    "bookId": "en-al-jalalayn",
    "language": "en",
    "surah": 44,
    "fromAyah": 47,
    "toAyah": 47,
    "title": "Tafsir Al-Jalalayn — English · 44:47",
    "body": "‘Seize him it will be said to the Zabāniya the Guards of Hell ‘seize the sinner’ and drag him read fa‘tilūhu or fa‘tulūhu haul him away violently and brutally to the midst of Hell-fire al-jahīm means the centre of the Fire.",
    "sourceLabel": "Tafsir Al-Jalalayn — English",
    "tags": [
      "en-al-jalalayn",
      "en",
      "foundational"
    ]
  },
  {
    "id": "en-al-jalalayn-44-48",
    "bookId": "en-al-jalalayn",
    "language": "en",
    "surah": 44,
    "fromAyah": 48,
    "toAyah": 48,
    "title": "Tafsir Al-Jalalayn — English · 44:48",
    "body": "Then pour over his head the torture of boiling water!’ that is to say the boiling water which is ever-torturous this use of ‘the torture of boiling water’ is rhetorically more intense than what is stated by the verse boiling water will be poured over their heads Q. 2219.",
    "sourceLabel": "Tafsir Al-Jalalayn — English",
    "tags": [
      "en-al-jalalayn",
      "en",
      "foundational"
    ]
  },
  {
    "id": "en-al-jalalayn-44-49",
    "bookId": "en-al-jalalayn",
    "language": "en",
    "surah": 44,
    "fromAyah": 49,
    "toAyah": 49,
    "title": "Tafsir Al-Jalalayn — English · 44:49",
    "body": "And it will be said to him ‘Taste! that is taste the chastisement. Indeed you are the mighty the noble one! as you claimed when you used to say ‘There is nothing between its two mountains sc. Mecca that is mightier or nobler than me!’",
    "sourceLabel": "Tafsir Al-Jalalayn — English",
    "tags": [
      "en-al-jalalayn",
      "en",
      "foundational"
    ]
  },
  {
    "id": "en-al-jalalayn-44-5",
    "bookId": "en-al-jalalayn",
    "language": "en",
    "surah": 44,
    "fromAyah": 5,
    "toAyah": 5,
    "title": "Tafsir Al-Jalalayn — English · 44:5",
    "body": "As an ordinance a distinguishing from Us. Indeed We have been sending from your Lord messengers such as Muhammad (s) and those before him",
    "sourceLabel": "Tafsir Al-Jalalayn — English",
    "tags": [
      "en-al-jalalayn",
      "en",
      "foundational"
    ]
  },
  {
    "id": "en-al-jalalayn-44-50",
    "bookId": "en-al-jalalayn",
    "language": "en",
    "surah": 44,
    "fromAyah": 50,
    "toAyah": 50,
    "title": "Tafsir Al-Jalalayn — English · 44:50",
    "body": "And it will be said to them This that you see of the chastisement is indeed that which you used to doubt’ about which you used to be uncertain.",
    "sourceLabel": "Tafsir Al-Jalalayn — English",
    "tags": [
      "en-al-jalalayn",
      "en",
      "foundational"
    ]
  },
  {
    "id": "en-al-jalalayn-44-51",
    "bookId": "en-al-jalalayn",
    "language": "en",
    "surah": 44,
    "fromAyah": 51,
    "toAyah": 51,
    "title": "Tafsir Al-Jalalayn — English · 44:51",
    "body": "Assuredly the God-fearing will be in a secure place a seat in which there will be security from all fear",
    "sourceLabel": "Tafsir Al-Jalalayn — English",
    "tags": [
      "en-al-jalalayn",
      "en",
      "foundational"
    ]
  },
  {
    "id": "en-al-jalalayn-44-52",
    "bookId": "en-al-jalalayn",
    "language": "en",
    "surah": 44,
    "fromAyah": 52,
    "toAyah": 52,
    "title": "Tafsir Al-Jalalayn — English · 44:52",
    "body": "amid gardens orchards and springs",
    "sourceLabel": "Tafsir Al-Jalalayn — English",
    "tags": [
      "en-al-jalalayn",
      "en",
      "foundational"
    ]
  },
  {
    "id": "en-al-jalalayn-44-53",
    "bookId": "en-al-jalalayn",
    "language": "en",
    "surah": 44,
    "fromAyah": 53,
    "toAyah": 53,
    "title": "Tafsir Al-Jalalayn — English · 44:53",
    "body": "dressed in fine silk and heavy silk brocade that is to say in fine and thick silks sundusin wa’stabraqin respectively sitting face to face mutaqābilīna is a circumstantial qualifier that is to say they do not look upon each other backs since the couches revolve with them in them.",
    "sourceLabel": "Tafsir Al-Jalalayn — English",
    "tags": [
      "en-al-jalalayn",
      "en",
      "foundational"
    ]
  },
  {
    "id": "en-al-jalalayn-44-54",
    "bookId": "en-al-jalalayn",
    "language": "en",
    "surah": 44,
    "fromAyah": 54,
    "toAyah": 54,
    "title": "Tafsir Al-Jalalayn — English · 44:54",
    "body": "So shall it be an implied al-amru ‘the matter’ should be read as preceding this; and We shall pair them either in conjugality or meaning We shall join them with houris of beautiful eyes women of the fairest complexion with wide and beautiful eyes.",
    "sourceLabel": "Tafsir Al-Jalalayn — English",
    "tags": [
      "en-al-jalalayn",
      "en",
      "foundational"
    ]
  },
  {
    "id": "en-al-jalalayn-44-55",
    "bookId": "en-al-jalalayn",
    "language": "en",
    "surah": 44,
    "fromAyah": 55,
    "toAyah": 55,
    "title": "Tafsir Al-Jalalayn — English · 44:55",
    "body": "They will call they will request from servants therein that is in Paradise to bring every fruit thereof remaining secure in their knowledge that it will not come to an end or cause harm and secure from all danger āminīna ‘secure’ is a circumstantial qualifier’.",
    "sourceLabel": "Tafsir Al-Jalalayn — English",
    "tags": [
      "en-al-jalalayn",
      "en",
      "foundational"
    ]
  },
  {
    "id": "en-al-jalalayn-44-56",
    "bookId": "en-al-jalalayn",
    "language": "en",
    "surah": 44,
    "fromAyah": 56,
    "toAyah": 56,
    "title": "Tafsir Al-Jalalayn — English · 44:56",
    "body": "They will not taste death therein other than the first death namely the one that came in this world after they had lived in it some scholars think that illā ‘other than’ here means ba‘da ‘after’. And He will shield them from the chastisement of Hell-fire —",
    "sourceLabel": "Tafsir Al-Jalalayn — English",
    "tags": [
      "en-al-jalalayn",
      "en",
      "foundational"
    ]
  },
  {
    "id": "en-al-jalalayn-44-57",
    "bookId": "en-al-jalalayn",
    "language": "en",
    "surah": 44,
    "fromAyah": 57,
    "toAyah": 57,
    "title": "Tafsir Al-Jalalayn — English · 44:57",
    "body": "a bounty from your Lord fadlan is a verbal noun with the sense of tafaddulan and is in the accusative dependent status because of an implied preceding tafaddala. That is the supreme triumph.",
    "sourceLabel": "Tafsir Al-Jalalayn — English",
    "tags": [
      "en-al-jalalayn",
      "en",
      "foundational"
    ]
  },
  {
    "id": "en-al-jalalayn-44-58",
    "bookId": "en-al-jalalayn",
    "language": "en",
    "surah": 44,
    "fromAyah": 58,
    "toAyah": 58,
    "title": "Tafsir Al-Jalalayn — English · 44:58",
    "body": "For We have made it easy We have facilitated the Qur’ān in your tongue in your language so that the Arabs may understand it from you that perhaps they may remember that perhaps they may be admonished and become believers — but they do not believe.",
    "sourceLabel": "Tafsir Al-Jalalayn — English",
    "tags": [
      "en-al-jalalayn",
      "en",
      "foundational"
    ]
  },
  {
    "id": "en-al-jalalayn-44-59",
    "bookId": "en-al-jalalayn",
    "language": "en",
    "surah": 44,
    "fromAyah": 59,
    "toAyah": 59,
    "title": "Tafsir Al-Jalalayn — English · 44:59",
    "body": "So be on the look out await their destruction. Indeed they too are on the look out for your death — this was before the revelation of the command to struggle against them.",
    "sourceLabel": "Tafsir Al-Jalalayn — English",
    "tags": [
      "en-al-jalalayn",
      "en",
      "foundational"
    ]
  },
  {
    "id": "en-al-jalalayn-44-6",
    "bookId": "en-al-jalalayn",
    "language": "en",
    "surah": 44,
    "fromAyah": 6,
    "toAyah": 6,
    "title": "Tafsir Al-Jalalayn — English · 44:6",
    "body": "as a mercy out of compassion for those to whom these messengers have been sent. Surely He is the Hearer of their sayings the Knower of their actions.",
    "sourceLabel": "Tafsir Al-Jalalayn — English",
    "tags": [
      "en-al-jalalayn",
      "en",
      "foundational"
    ]
  },
  {
    "id": "en-al-jalalayn-44-7",
    "bookId": "en-al-jalalayn",
    "language": "en",
    "surah": 44,
    "fromAyah": 7,
    "toAyah": 7,
    "title": "Tafsir Al-Jalalayn — English · 44:7",
    "body": "Lord of the heavens and the earth and all that is between them read rabbu’l-samāwāti in the nominative to understand it as a third predicate; or read rabbi’l-samāwāti as a substitution for rabbika ‘your Lord’ if you should be certain O people of Mecca that God exalted be He is the Lord of the heavens and the earth then also be certain that Muhammad (s) is His Messenger.",
    "sourceLabel": "Tafsir Al-Jalalayn — English",
    "tags": [
      "en-al-jalalayn",
      "en",
      "foundational"
    ]
  },
  {
    "id": "en-al-jalalayn-44-8",
    "bookId": "en-al-jalalayn",
    "language": "en",
    "surah": 44,
    "fromAyah": 8,
    "toAyah": 8,
    "title": "Tafsir Al-Jalalayn — English · 44:8",
    "body": "There is no god except Him. He gives life and brings death. Your Lord and the Lord of your forefathers.",
    "sourceLabel": "Tafsir Al-Jalalayn — English",
    "tags": [
      "en-al-jalalayn",
      "en",
      "foundational"
    ]
  },
  {
    "id": "en-al-jalalayn-44-9",
    "bookId": "en-al-jalalayn",
    "language": "en",
    "surah": 44,
    "fromAyah": 9,
    "toAyah": 9,
    "title": "Tafsir Al-Jalalayn — English · 44:9",
    "body": "Nay but they linger in doubt concerning the Resurrection playing in mockery of you O Muhammad (s) and so he said ‘My God assist me against them with seven years of drought like the seven of Joseph’.",
    "sourceLabel": "Tafsir Al-Jalalayn — English",
    "tags": [
      "en-al-jalalayn",
      "en",
      "foundational"
    ]
  }
]
